[
    {
        "model": "users.user",
        "pk": 1,
        "fields": {
            "password": "pbkdf2_sha256$600000$ra1rdEF0aZkbnLdou7nDoW$yuApniZRaLeQELv3/2b6d7grHaIyfYRat1kmjBu3q5M=",
            "last_login": "2024-01-30T20:03:14.129Z",
            "is_superuser": true,
            "username": "suser",
            "first_name": "",
            "last_name": "",
            "email": "",
            "is_staff": true,
            "is_active": true,
            "date_joined": "2024-01-30T20:02:08.666Z",
            "groups": [],
            "user_permissions": [],
            "favourites": []
        }
    }
]